lsd/__init__.py
lsd/base.py
lsd/config.py
lsd/design/ae.yaml
lsd/design/dr.yaml
lsd/design/templates/ae/hyperparameter_multiverse/CIFAR10.yaml
lsd/design/templates/ae/hyperparameter_multiverse/FashionMNIST.yaml
lsd/design/templates/ae/hyperparameter_multiverse/MNIST.yaml
lsd/design/templates/ae/hyperparameter_multiverse/XYC.yaml
lsd/design/templates/ae/hyperparameter_multiverse/celebA.yaml
lsd/design/templates/ae/hyperparameter_multiverse/dsprites.yaml
lsd/design/templates/ae/hyperparameter_multiverse/teapots.yaml
lsd/design/templates/ae/implementation_multiverse/CIFAR10_batch_size.yaml
lsd/design/templates/ae/implementation_multiverse/CIFAR10_hidden_dims.yaml
lsd/design/templates/ae/implementation_multiverse/CIFAR10_learning_rate.yaml
lsd/design/templates/ae/implementation_multiverse/CIFAR10_sample_size.yaml
lsd/design/templates/ae/implementation_multiverse/CIFAR10_train_test.yaml
lsd/design/templates/ae/implementation_multiverse/FashionMNIST_batch_size.yaml
lsd/design/templates/ae/implementation_multiverse/FashionMNIST_hidden_dims.yaml
lsd/design/templates/ae/implementation_multiverse/FashionMNIST_learning_rate.yaml
lsd/design/templates/ae/implementation_multiverse/FashionMNIST_sample_size.yaml
lsd/design/templates/ae/implementation_multiverse/FashionMNIST_train_test.yaml
lsd/design/templates/ae/implementation_multiverse/MNIST_batch_size.yaml
lsd/design/templates/ae/implementation_multiverse/MNIST_hidden_dims.yaml
lsd/design/templates/ae/implementation_multiverse/MNIST_learning_rate.yaml
lsd/design/templates/ae/implementation_multiverse/MNIST_sample_size.yaml
lsd/design/templates/ae/implementation_multiverse/MNIST_train_test.yaml
lsd/design/templates/ae/implementation_multiverse/celebA_batch_size.yaml
lsd/design/templates/ae/implementation_multiverse/celebA_hidden_dims.yaml
lsd/design/templates/ae/implementation_multiverse/celebA_learning_rate.yaml
lsd/design/templates/ae/implementation_multiverse/celebA_sample_size.yaml
presto_multiverse-0.1.3.dist-info/LICENSE
presto_multiverse-0.1.3.dist-info/METADATA
presto_multiverse-0.1.3.dist-info/WHEEL
presto_multiverse-0.1.3.dist-info/RECORD
