Metadata-Version: 2.1
Name: presto-multiverse
Version: 0.1.3
Summary: Presto: Projected Embedding Similarty based on Topological Overlays
License: BSD-3
Author: jeremy.wayland
Author-email: jeremy.don.wayland@gmail.com
Requires-Python: >=3.11,<4.0
Classifier: License :: Other/Proprietary License
Classifier: Programming Language :: Python :: 3
Classifier: Programming Language :: Python :: 3.11
Classifier: Programming Language :: Python :: 3.12
Requires-Dist: gudhi (>=3.9.0,<4.0.0)
Requires-Dist: networkx (>=3.2.1,<4.0.0)
Requires-Dist: numpy (>=1.26.4,<2.0.0)
Requires-Dist: omegaconf (>=2.3.0,<3.0.0)
Requires-Dist: phate (>=1.0.11,<2.0.0)
Requires-Dist: pytest (>=8.0.2,<9.0.0)
Requires-Dist: python-dotenv (>=1.0.1,<2.0.0)
Requires-Dist: scikit-learn (>=1.4.1.post1,<2.0.0)
Requires-Dist: torch (>=2.3.1,<3.0.0)
Requires-Dist: torch-geometric (>=2.5.3,<3.0.0)
Requires-Dist: torchvision (>=0.18.1,<0.19.0)
Requires-Dist: tqdm (>=4.66.2,<5.0.0)
Requires-Dist: umap-learn (>=0.5.6,<0.6.0)
Requires-Dist: wandb (>=0.16.4,<0.17.0)
